MANIFEST.in
bootstrap.py
buildout.cfg
setup.cfg
setup.py
docs/Makefile
docs/conf.py
docs/index.rst
docs/make.bat
docs/sample.rst
src/AUTHORS.txt
src/HISTORY.txt
src/LICENSE.txt
src/README.txt
src/TODOS.txt
src/sphinxjp/__init__.py
src/sphinxjp.themes.solarized.egg-info/PKG-INFO
src/sphinxjp.themes.solarized.egg-info/SOURCES.txt
src/sphinxjp.themes.solarized.egg-info/dependency_links.txt
src/sphinxjp.themes.solarized.egg-info/entry_points.txt
src/sphinxjp.themes.solarized.egg-info/namespace_packages.txt
src/sphinxjp.themes.solarized.egg-info/not-zip-safe
src/sphinxjp.themes.solarized.egg-info/requires.txt
src/sphinxjp.themes.solarized.egg-info/top_level.txt
src/sphinxjp/themes/__init__.py
src/sphinxjp/themes/solarized/__init__.py
src/sphinxjp/themes/solarized/templates/solarized/layout.html
src/sphinxjp/themes/solarized/templates/solarized/theme.conf
src/sphinxjp/themes/solarized/templates/solarized/static/.default.css_t.swo
src/sphinxjp/themes/solarized/templates/solarized/static/default.css_t
src/sphinxjp/themes/solarized/templates/solarized/static/information.png
src/sphinxjp/themes/solarized/templates/solarized/static/note.png
src/sphinxjp/themes/solarized/templates/solarized/static/topic.png
src/sphinxjp/themes/solarized/templates/solarized/static/warning.png