Metadata-Version: 1.0
Name: sphinxjp.themes.solarized
Version: 0.1.0
Summary: A sphinx theme based on solarized color scheme. #sphinxjp
Home-page: http://bitbucket.org/miiton/sphinxjp.themes.solarized
Author: Takahiro MINAMI
Author-email: vo dot gu dot ba dot miiton at gmail dot com
License: MIT
Keywords: sphinx,reStructuredText,solarized
Platform: UNKNOWN
Classifier: Development Status :: 4 - Beta
Classifier: License :: OSI Approved :: MIT License
Classifier: Programming Language :: Python
Classifier: Topic :: Software Development
Classifier: Topic :: Software Development :: Documentation
Classifier: Topic :: Text Processing :: Markup
